lib/__init__.py
lib/config_loader.py
lib/decorators.py
configserver_py-1.0.8.dist-info/METADATA
configserver_py-1.0.8.dist-info/WHEEL
configserver_py-1.0.8.dist-info/top_level.txt
configserver_py-1.0.8.dist-info/RECORD
