Metadata-Version: 2.4
Name: configserver-py
Version: 1.0.8
Summary: A Python library for consuming Spring Cloud Config Server and managing configurations.
Home-page: https://github.com/your-repo/backstage-lib
Author: Luis Martinez
Author-email: linuxlondo1211@gmail.com
Classifier: Programming Language :: Python :: 3
Classifier: License :: OSI Approved :: MIT License
Classifier: Operating System :: OS Independent
Requires-Python: >=3.6
Requires-Dist: pyyaml
Requires-Dist: requests
Dynamic: author
Dynamic: author-email
Dynamic: classifier
Dynamic: home-page
Dynamic: requires-dist
Dynamic: requires-python
Dynamic: summary
